open_wodoo/__init__.py
open_wodoo/__main__.py
open_wodoo/cli.py
open_wodoo/commands/__init__.py
open_wodoo/commands/bootstrap.py
open_wodoo/commands/launch.py
open_wodoo/commands/makedev.py
open_wodoo/commands/rpc/__init__.py
open_wodoo/commands/rpc/cli.py
open_wodoo/commands/rpc/importer.py
open_wodoo/commands/rpc/modules.py
open_wodoo/commands/rpc/translations.py
open_wodoo/commands/shell.py
open_wodoo/commands/test.py
open_wodoo/commands/update.py
open_wodoo/git/__init__.py
open_wodoo/git/git_odoo.py
open_wodoo/git/git_odoo_addons.py
open_wodoo/git/git_repo.py
open_wodoo/git/git_url.py
open_wodoo/git/zip_download.py
open_wodoo/helpers/__init__.py
open_wodoo/helpers/cli.py
open_wodoo/helpers/odoo_files.py
open_wodoo/helpers/repospec.py
open_wodoo-0.0.2.dist-info/entry_points.txt
open_wodoo-0.0.2.dist-info/LICENSE
open_wodoo-0.0.2.dist-info/WHEEL
open_wodoo-0.0.2.dist-info/METADATA
open_wodoo-0.0.2.dist-info/RECORD
