Metadata-Version: 2.1
Name: open-wodoo
Version: 0.0.2
Summary: Wrapper around Odoo-Bin with some convinience RPC functions.
License: LGPL-3
Author: Joshua Kreuder
Author-email: Joshua_Kreuder@outlook.com
Requires-Python: >=3.8,<3.11
Classifier: License :: Other/Proprietary License
Classifier: Programming Language :: Python :: 3
Classifier: Programming Language :: Python :: 3.8
Classifier: Programming Language :: Python :: 3.9
Classifier: Programming Language :: Python :: 3.10
Requires-Dist: gitpython (==3.1.27)
Requires-Dist: openupgradelib (==3.3.4)
Requires-Dist: python-dotenv (==0.20.0)
Requires-Dist: rich (==12.6.0)
Requires-Dist: ruamel-yaml (==0.17.21)
Requires-Dist: typer[all] (>=0.7.0,<0.8.0)
Requires-Dist: wodoo-rpc (==0.0.2)
